simgle/__init__.py
simgle/cli.py
simgle/utils.py
simgle-1.1.2.dist-info/METADATA
simgle-1.1.2.dist-info/WHEEL
simgle-1.1.2.dist-info/entry_points.txt
simgle-1.1.2.dist-info/licenses/LICENSE
simgle-1.1.2.dist-info/RECORD
