Metadata-Version: 2.4
Name: simgle
Version: 1.1.2
Summary: Save time and money by easily finding the cheapest virtual numbers on OnlineSim.
Project-URL: Homepage, https://github.com/zelevar/simgle
Author: zelevar
License-Expression: MIT
License-File: LICENSE
Requires-Python: >=3.9
Requires-Dist: requests>=2.32.3
